janos/__init__.py
janos/janos.py
janos-0.0.9.dist-info/METADATA
janos-0.0.9.dist-info/WHEEL
janos-0.0.9.dist-info/top_level.txt
janos-0.0.9.dist-info/RECORD
