Metadata-Version: 2.1
Name: janos
Version: 0.0.9
Summary: JANOS
Home-page: http://janos.opt-operations.com
Author: David Bergman
Author-email: david.bergman@uconn.edu
License: UNKNOWN
Platform: UNKNOWN
Classifier: Programming Language :: Python :: 3
Classifier: License :: OSI Approved :: MIT License
Classifier: Operating System :: OS Independent
Requires-Python: >=3.5
